scilens/LICENSE
scilens/__init__.py
scilens/app.py
scilens/cli/__init__.py
scilens/cli/cglb.py
scilens/cli/config.py
scilens/cli/info.py
scilens/cli/main.py
scilens/components/__init__.py
scilens/components/analyse_folder.py
scilens/components/compare_2_files.py
scilens/components/compare_errors.py
scilens/components/compare_floats.py
scilens/components/compare_folders.py
scilens/components/compare_models.py
scilens/components/executor.py
scilens/components/file_reader.py
scilens/components/num/vectors.py
scilens/config/__init__.py
scilens/config/cli_run_options.py
scilens/config/env_var.py
scilens/config/load.py
scilens/config/models/__init__.py
scilens/config/models/app.py
scilens/config/models/base.py
scilens/config/models/compare.py
scilens/config/models/compare_float_thresholds.py
scilens/config/models/execute.py
scilens/config/models/execute_and_compare.py
scilens/config/models/file_reader.py
scilens/config/models/reader_format_cols.py
scilens/config/models/reader_format_csv.py
scilens/config/models/reader_format_netcdf.py
scilens/config/models/reader_format_trees.py
scilens/config/models/reader_format_txt.py
scilens/config/models/reader_format_txt_fixed_cols.py
scilens/config/models/reader_metrics.py
scilens/config/models/readers.py
scilens/config/models/report.py
scilens/config/models/report_html.py
scilens/config/models/report_output.py
scilens/helpers/assets.py
scilens/helpers/search_and_index.py
scilens/helpers/templates/index.html
scilens/helpers/templates/style.css
scilens/processors/__init__.py
scilens/processors/analyse.py
scilens/processors/compare.py
scilens/processors/execute_and_compare.py
scilens/processors/models/__init__.py
scilens/processors/models/results.py
scilens/processors/processor_interface.py
scilens/readers/__init__.py
scilens/readers/cols_dataset.py
scilens/readers/exceptions.py
scilens/readers/mat_dataset.py
scilens/readers/reader_csv.py
scilens/readers/reader_interface.py
scilens/readers/reader_json.py
scilens-0.5.1.dist-info/METADATA
scilens-0.5.1.dist-info/WHEEL
scilens-0.5.1.dist-info/entry_points.txt
scilens-0.5.1.dist-info/RECORD
