Metadata-Version: 2.1
Name: scilens
Version: 0.5.1
Summary: A CesGensLaB framework for data collecting and deep analysis
Home-page: https://scilens.dev
License: Proprietary
Author: CesGensLaB
Author-email: contact@cesgenlab.fr
Requires-Python: >=3.10,<4.0
Classifier: License :: Other/Proprietary License
Classifier: Programming Language :: Python :: 3
Classifier: Programming Language :: Python :: 3.10
Classifier: Programming Language :: Python :: 3.11
Classifier: Programming Language :: Python :: 3.12
Classifier: Programming Language :: Python :: 3.13
Requires-Dist: coloredlogs (>=15.0.1,<16.0.0)
Requires-Dist: jinja2 (>=3.1.6,<4.0.0)
Requires-Dist: numpy (>=2.2.6,<3.0.0)
Requires-Dist: pydantic (>=2.11.7,<3.0.0)
Requires-Dist: pyyaml (>=6.0.2,<7.0.0)
Requires-Dist: requests (>=2.32.5,<3.0.0)
Requires-Dist: rich-click (>=1.8.9,<2.0.0)
Project-URL: Documentation, https://scilens.dev/docs
